setup.py
nagios/__init__.py
nagios/log.py
nagios_nsca.egg-info/PKG-INFO
nagios_nsca.egg-info/SOURCES.txt
nagios_nsca.egg-info/dependency_links.txt
nagios_nsca.egg-info/top_level.txt