Metadata-Version: 1.1
Name: nagios-nsca
Version: 1.1.1
Summary: Nagios passive checks support
Home-page: https://github.com/COEXCZ/nagios-nsca
Author: Jan Češpivo, COEX CZ s.r.o (http://www.coex.cz)
Author-email: jan.cespivo@gmail.com
License: LICENSE
Platform: UNKNOWN
Classifier: Development Status :: 5 - Production/Stable
Classifier: Environment :: Web Environment
Classifier: Intended Audience :: Developers
Classifier: License :: OSI Approved :: GNU Lesser General Public License v3 (LGPLv3)
Classifier: Operating System :: OS Independent
Classifier: Programming Language :: Python
